{
    "Meta Data": {
        "1. Information": "Intraday (60min) open, high, low, close prices and volume - DATA DELAYED BY 15 MINUTES",
        "2. Symbol": "TMUS",
        "3. Last Refreshed": "2025-11-06 15:00:00",
        "4. Interval": "60min",
        "5. Output Size": "Full size",
        "6. Time Zone": "US/Eastern"
    },
    "Time Series (60min)": {
        "2025-10-30 15:00:00": {
            "1. open": "210.8417",
            "2. high": "211.7600",
            "3. low": "209.5800",
            "4. close": "210.6600",
            "5. volume": "1531234"
        },
        "2025-10-30 14:00:00": {
            "1. open": "211.4300",
            "2. high": "211.6300",
            "3. low": "210.3950",
            "4. close": "210.8700",
            "5. volume": "484950"
        },
        "2025-10-30 13:00:00": {
            "1. open": "212.6700",
            "2. high": "212.6700",
            "3. low": "211.3500",
            "4. close": "211.4300",
            "5. volume": "396481"
        },
        "2025-10-30 12:00:00": {
            "1. open": "212.8850",
            "2. high": "213.1200",
            "3. low": "211.7000",
            "4. close": "212.7200",
            "5. volume": "471638"
        },
        "2025-10-30 11:00:00": {
            "1. open": "212.9200",
            "2. high": "213.4100",
            "3. low": "212.3200",
            "4. close": "212.8875",
            "5. volume": "556296"
        },
        "2025-10-30 10:00:00": {
            "1. open": "215.0700",
            "2. high": "215.6700",
            "3. low": "212.3800",
            "4. close": "212.8800",
            "5. volume": "750863"
        },
        "2025-10-29 15:00:00": {
            "1. open": "213.9600",
            "2. high": "215.0100",
            "3. low": "213.3200",
            "4. close": "215.0100",
            "5. volume": "1261922"
        },
        "2025-10-29 14:00:00": {
            "1. open": "212.4950",
            "2. high": "214.1800",
            "3. low": "212.1200",
            "4. close": "213.9600",
            "5. volume": "744623"
        },
        "2025-10-29 13:00:00": {
            "1. open": "213.3000",
            "2. high": "213.5000",
            "3. low": "212.2200",
            "4. close": "212.4950",
            "5. volume": "573676"
        },
        "2025-10-29 12:00:00": {
            "1. open": "214.1450",
            "2. high": "215.0400",
            "3. low": "213.2700",
            "4. close": "213.3055",
            "5. volume": "526543"
        },
        "2025-10-29 11:00:00": {
            "1. open": "215.6550",
            "2. high": "215.7000",
            "3. low": "213.7500",
            "4. close": "214.0800",
            "5. volume": "868876"
        },
        "2025-10-29 10:00:00": {
            "1. open": "214.7600",
            "2. high": "217.3200",
            "3. low": "213.7200",
            "4. close": "215.6400",
            "5. volume": "1492231"
        },
        "2025-10-28 15:00:00": {
            "1. open": "220.9000",
            "2. high": "221.2000",
            "3. low": "219.6900",
            "4. close": "219.9500",
            "5. volume": "1119377"
        },
        "2025-10-28 14:00:00": {
            "1. open": "220.3650",
            "2. high": "221.0500",
            "3. low": "220.3650",
            "4. close": "220.9200",
            "5. volume": "300873"
        },
        "2025-10-28 13:00:00": {
            "1. open": "221.8100",
            "2. high": "222.1600",
            "3. low": "220.2150",
            "4. close": "220.3900",
            "5. volume": "416229"
        },
        "2025-10-28 12:00:00": {
            "1. open": "221.2600",
            "2. high": "222.8300",
            "3. low": "221.2300",
            "4. close": "221.8014",
            "5. volume": "551509"
        },
        "2025-10-28 11:00:00": {
            "1. open": "220.8950",
            "2. high": "221.4800",
            "3. low": "220.6187",
            "4. close": "221.3200",
            "5. volume": "371590"
        },
        "2025-10-28 10:00:00": {
            "1. open": "219.2000",
            "2. high": "220.9700",
            "3. low": "219.2000",
            "4. close": "220.8400",
            "5. volume": "520255"
        },
        "2025-10-27 15:00:00": {
            "1. open": "220.5750",
            "2. high": "221.6400",
            "3. low": "220.4900",
            "4. close": "220.6100",
            "5. volume": "1296080"
        },
        "2025-10-27 14:00:00": {
            "1. open": "220.3700",
            "2. high": "220.9100",
            "3. low": "220.2400",
            "4. close": "220.5750",
            "5. volume": "395546"
        },
        "2025-10-27 13:00:00": {
            "1. open": "220.1200",
            "2. high": "220.5500",
            "3. low": "219.9022",
            "4. close": "220.3600",
            "5. volume": "516578"
        },
        "2025-10-27 12:00:00": {
            "1. open": "219.5500",
            "2. high": "220.5700",
            "3. low": "219.5500",
            "4. close": "220.0800",
            "5. volume": "529574"
        },
        "2025-10-27 11:00:00": {
            "1. open": "218.9550",
            "2. high": "219.7100",
            "3. low": "218.0000",
            "4. close": "219.4800",
            "5. volume": "538730"
        },
        "2025-10-27 10:00:00": {
            "1. open": "215.9550",
            "2. high": "219.0000",
            "3. low": "215.8610",
            "4. close": "218.9550",
            "5. volume": "857660"
        },
        "2025-10-24 15:00:00": {
            "1. open": "216.7100",
            "2. high": "217.8200",
            "3. low": "215.8200",
            "4. close": "217.7700",
            "5. volume": "1138194"
        },
        "2025-10-24 14:00:00": {
            "1. open": "217.1150",
            "2. high": "217.1350",
            "3. low": "216.0800",
            "4. close": "216.7300",
            "5. volume": "500839"
        },
        "2025-10-24 13:00:00": {
            "1. open": "216.8900",
            "2. high": "217.5400",
            "3. low": "216.4200",
            "4. close": "217.1300",
            "5. volume": "387291"
        },
        "2025-10-24 12:00:00": {
            "1. open": "216.1200",
            "2. high": "217.4900",
            "3. low": "215.9100",
            "4. close": "216.9700",
            "5. volume": "524586"
        },
        "2025-10-24 11:00:00": {
            "1. open": "216.3200",
            "2. high": "216.6200",
            "3. low": "215.6000",
            "4. close": "216.0850",
            "5. volume": "643041"
        },
        "2025-10-24 10:00:00": {
            "1. open": "217.2900",
            "2. high": "218.6400",
            "3. low": "216.1100",
            "4. close": "216.3500",
            "5. volume": "768711"
        },
        "2025-10-23 15:00:00": {
            "1. open": "219.3450",
            "2. high": "220.3399",
            "3. low": "218.9000",
            "4. close": "220.0000",
            "5. volume": "1595434"
        },
        "2025-10-23 14:00:00": {
            "1. open": "219.2934",
            "2. high": "220.6400",
            "3. low": "219.0000",
            "4. close": "219.3750",
            "5. volume": "966788"
        },
        "2025-10-23 13:00:00": {
            "1. open": "218.2100",
            "2. high": "219.3100",
            "3. low": "217.3500",
            "4. close": "219.2600",
            "5. volume": "604210"
        },
        "2025-10-23 12:00:00": {
            "1. open": "216.4000",
            "2. high": "218.4150",
            "3. low": "215.8155",
            "4. close": "218.1800",
            "5. volume": "993588"
        },
        "2025-10-23 11:00:00": {
            "1. open": "218.9550",
            "2. high": "219.2000",
            "3. low": "216.1200",
            "4. close": "216.4500",
            "5. volume": "1200404"
        },
        "2025-10-23 10:00:00": {
            "1. open": "221.6500",
            "2. high": "222.0600",
            "3. low": "218.9000",
            "4. close": "218.9000",
            "5. volume": "1436948"
        },
        "2025-10-22 15:00:00": {
            "1. open": "226.5450",
            "2. high": "227.2100",
            "3. low": "225.7600",
            "4. close": "227.0900",
            "5. volume": "1391766"
        },
        "2025-10-22 14:00:00": {
            "1. open": "226.6400",
            "2. high": "227.5600",
            "3. low": "226.0300",
            "4. close": "226.5300",
            "5. volume": "485022"
        },
        "2025-10-22 13:00:00": {
            "1. open": "227.1500",
            "2. high": "227.1500",
            "3. low": "225.7000",
            "4. close": "226.6400",
            "5. volume": "492279"
        },
        "2025-10-22 12:00:00": {
            "1. open": "227.2300",
            "2. high": "227.2600",
            "3. low": "226.3300",
            "4. close": "227.1500",
            "5. volume": "402798"
        },
        "2025-10-22 11:00:00": {
            "1. open": "225.8700",
            "2. high": "227.8900",
            "3. low": "225.6600",
            "4. close": "227.2900",
            "5. volume": "558200"
        },
        "2025-10-22 10:00:00": {
            "1. open": "223.7400",
            "2. high": "226.4950",
            "3. low": "222.5100",
            "4. close": "226.0700",
            "5. volume": "781896"
        },
        "2025-10-21 15:00:00": {
            "1. open": "229.3500",
            "2. high": "229.7000",
            "3. low": "228.4800",
            "4. close": "229.0000",
            "5. volume": "805542"
        },
        "2025-10-21 14:00:00": {
            "1. open": "229.4300",
            "2. high": "230.0900",
            "3. low": "229.1700",
            "4. close": "229.3750",
            "5. volume": "287855"
        },
        "2025-10-21 13:00:00": {
            "1. open": "230.0200",
            "2. high": "230.2100",
            "3. low": "229.3100",
            "4. close": "229.4300",
            "5. volume": "218230"
        },
        "2025-10-21 12:00:00": {
            "1. open": "229.3700",
            "2. high": "230.2300",
            "3. low": "228.9900",
            "4. close": "230.0800",
            "5. volume": "355581"
        },
        "2025-10-21 11:00:00": {
            "1. open": "229.8200",
            "2. high": "229.9700",
            "3. low": "228.7500",
            "4. close": "229.3900",
            "5. volume": "295917"
        },
        "2025-10-21 10:00:00": {
            "1. open": "229.0300",
            "2. high": "230.1200",
            "3. low": "228.7500",
            "4. close": "229.8300",
            "5. volume": "383110"
        },
        "2025-10-20 15:00:00": {
            "1. open": "230.0200",
            "2. high": "230.5400",
            "3. low": "229.2600",
            "4. close": "230.0500",
            "5. volume": "1036129"
        },
        "2025-10-20 14:00:00": {
            "1. open": "229.7500",
            "2. high": "230.2500",
            "3. low": "229.6240",
            "4. close": "230.0700",
            "5. volume": "320694"
        },
        "2025-10-20 13:00:00": {
            "1. open": "229.0850",
            "2. high": "229.7300",
            "3. low": "228.9800",
            "4. close": "229.7200",
            "5. volume": "292584"
        },
        "2025-10-20 12:00:00": {
            "1. open": "227.8500",
            "2. high": "229.0650",
            "3. low": "227.4360",
            "4. close": "229.0650",
            "5. volume": "213022"
        },
        "2025-10-20 11:00:00": {
            "1. open": "226.7600",
            "2. high": "228.1100",
            "3. low": "226.4000",
            "4. close": "227.8700",
            "5. volume": "363324"
        },
        "2025-10-20 10:00:00": {
            "1. open": "228.1800",
            "2. high": "228.4350",
            "3. low": "226.6716",
            "4. close": "226.7800",
            "5. volume": "418846"
        },
        "2025-10-17 15:00:00": {
            "1. open": "229.1900",
            "2. high": "229.9500",
            "3. low": "229.1600",
            "4. close": "229.3300",
            "5. volume": "635533"
        },
        "2025-10-17 14:00:00": {
            "1. open": "228.4700",
            "2. high": "229.4900",
            "3. low": "228.4200",
            "4. close": "229.2100",
            "5. volume": "220099"
        },
        "2025-10-17 13:00:00": {
            "1. open": "228.1300",
            "2. high": "228.5300",
            "3. low": "227.3900",
            "4. close": "228.4100",
            "5. volume": "191873"
        },
        "2025-10-17 12:00:00": {
            "1. open": "228.8200",
            "2. high": "229.3700",
            "3. low": "228.1900",
            "4. close": "228.2150",
            "5. volume": "290524"
        },
        "2025-10-17 11:00:00": {
            "1. open": "227.2150",
            "2. high": "228.9100",
            "3. low": "227.1600",
            "4. close": "228.7500",
            "5. volume": "356070"
        },
        "2025-10-17 10:00:00": {
            "1. open": "227.6600",
            "2. high": "227.8700",
            "3. low": "226.9100",
            "4. close": "227.2150",
            "5. volume": "310580"
        },
        "2025-10-16 15:00:00": {
            "1. open": "225.7400",
            "2. high": "226.6800",
            "3. low": "225.2460",
            "4. close": "226.4500",
            "5. volume": "776791"
        },
        "2025-10-16 14:00:00": {
            "1. open": "225.6700",
            "2. high": "225.9000",
            "3. low": "225.3500",
            "4. close": "225.7200",
            "5. volume": "282835"
        },
        "2025-10-16 13:00:00": {
            "1. open": "226.4950",
            "2. high": "226.6900",
            "3. low": "225.6100",
            "4. close": "225.7100",
            "5. volume": "232230"
        },
        "2025-10-16 12:00:00": {
            "1. open": "227.6800",
            "2. high": "227.7800",
            "3. low": "226.1300",
            "4. close": "226.4950",
            "5. volume": "250665"
        },
        "2025-10-16 11:00:00": {
            "1. open": "229.1650",
            "2. high": "229.3750",
            "3. low": "227.5900",
            "4. close": "227.6800",
            "5. volume": "380034"
        },
        "2025-10-16 10:00:00": {
            "1. open": "228.8500",
            "2. high": "230.0700",
            "3. low": "227.9200",
            "4. close": "229.1900",
            "5. volume": "407066"
        },
        "2025-10-15 15:00:00": {
            "1. open": "227.7400",
            "2. high": "227.8950",
            "3. low": "226.3700",
            "4. close": "226.6700",
            "5. volume": "876360"
        },
        "2025-10-15 14:00:00": {
            "1. open": "227.3400",
            "2. high": "227.9000",
            "3. low": "227.2400",
            "4. close": "227.7600",
            "5. volume": "186973"
        },
        "2025-10-15 13:00:00": {
            "1. open": "228.9300",
            "2. high": "229.0900",
            "3. low": "226.6600",
            "4. close": "227.2250",
            "5. volume": "222962"
        },
        "2025-10-15 12:00:00": {
            "1. open": "228.1100",
            "2. high": "229.2500",
            "3. low": "227.8800",
            "4. close": "229.0150",
            "5. volume": "309433"
        },
        "2025-10-15 11:00:00": {
            "1. open": "228.6850",
            "2. high": "229.3100",
            "3. low": "228.0800",
            "4. close": "228.1422",
            "5. volume": "243907"
        },
        "2025-10-15 10:00:00": {
            "1. open": "228.4450",
            "2. high": "229.5300",
            "3. low": "228.4450",
            "4. close": "228.6850",
            "5. volume": "254172"
        },
        "2025-10-14 15:00:00": {
            "1. open": "229.7700",
            "2. high": "230.2050",
            "3. low": "229.1700",
            "4. close": "229.4100",
            "5. volume": "970418"
        },
        "2025-10-14 14:00:00": {
            "1. open": "229.6900",
            "2. high": "229.8300",
            "3. low": "229.4045",
            "4. close": "229.8000",
            "5. volume": "211685"
        },
        "2025-10-14 13:00:00": {
            "1. open": "229.4100",
            "2. high": "229.8300",
            "3. low": "229.2500",
            "4. close": "229.6700",
            "5. volume": "192586"
        },
        "2025-10-14 12:00:00": {
            "1. open": "229.2300",
            "2. high": "229.9350",
            "3. low": "229.1150",
            "4. close": "229.3500",
            "5. volume": "292287"
        },
        "2025-10-14 11:00:00": {
            "1. open": "228.7200",
            "2. high": "229.1600",
            "3. low": "228.1540",
            "4. close": "229.1450",
            "5. volume": "284037"
        },
        "2025-10-14 10:00:00": {
            "1. open": "227.6000",
            "2. high": "228.9250",
            "3. low": "227.1900",
            "4. close": "228.7200",
            "5. volume": "370873"
        },
        "2025-10-13 15:00:00": {
            "1. open": "225.5150",
            "2. high": "225.8100",
            "3. low": "224.0600",
            "4. close": "225.0500",
            "5. volume": "915401"
        },
        "2025-10-13 14:00:00": {
            "1. open": "225.0200",
            "2. high": "225.8400",
            "3. low": "224.8100",
            "4. close": "225.5150",
            "5. volume": "264522"
        },
        "2025-10-13 13:00:00": {
            "1. open": "226.6450",
            "2. high": "226.7400",
            "3. low": "224.5700",
            "4. close": "224.9400",
            "5. volume": "259881"
        },
        "2025-10-13 12:00:00": {
            "1. open": "227.5150",
            "2. high": "228.1300",
            "3. low": "226.1900",
            "4. close": "226.6450",
            "5. volume": "321643"
        },
        "2025-10-13 11:00:00": {
            "1. open": "226.9400",
            "2. high": "227.8100",
            "3. low": "226.7200",
            "4. close": "227.5300",
            "5. volume": "301732"
        },
        "2025-10-13 10:00:00": {
            "1. open": "227.3050",
            "2. high": "229.5000",
            "3. low": "226.7200",
            "4. close": "226.9400",
            "5. volume": "494796"
        },
        "2025-10-10 15:00:00": {
            "1. open": "228.4300",
            "2. high": "229.0700",
            "3. low": "227.8700",
            "4. close": "228.9600",
            "5. volume": "1282089"
        },
        "2025-10-10 14:00:00": {
            "1. open": "228.6100",
            "2. high": "228.8099",
            "3. low": "228.1479",
            "4. close": "228.3600",
            "5. volume": "312756"
        },
        "2025-10-10 13:00:00": {
            "1. open": "229.4850",
            "2. high": "229.8300",
            "3. low": "228.3900",
            "4. close": "228.7300",
            "5. volume": "461024"
        },
        "2025-10-10 12:00:00": {
            "1. open": "228.1950",
            "2. high": "229.6800",
            "3. low": "228.0800",
            "4. close": "229.5600",
            "5. volume": "482658"
        },
        "2025-10-10 11:00:00": {
            "1. open": "227.0650",
            "2. high": "231.0200",
            "3. low": "226.8201",
            "4. close": "228.2200",
            "5. volume": "945400"
        },
        "2025-10-10 10:00:00": {
            "1. open": "227.1900",
            "2. high": "227.8900",
            "3. low": "226.8300",
            "4. close": "227.1200",
            "5. volume": "313079"
        },
        "2025-10-09 15:00:00": {
            "1. open": "226.2500",
            "2. high": "226.7600",
            "3. low": "225.7600",
            "4. close": "226.1850",
            "5. volume": "888402"
        },
        "2025-10-09 14:00:00": {
            "1. open": "227.3900",
            "2. high": "227.4550",
            "3. low": "226.0600",
            "4. close": "226.2000",
            "5. volume": "234195"
        },
        "2025-10-09 13:00:00": {
            "1. open": "226.9600",
            "2. high": "227.5400",
            "3. low": "226.9400",
            "4. close": "227.3900",
            "5. volume": "209518"
        },
        "2025-10-09 12:00:00": {
            "1. open": "227.0900",
            "2. high": "228.0700",
            "3. low": "226.4900",
            "4. close": "227.0050",
            "5. volume": "215975"
        },
        "2025-10-09 11:00:00": {
            "1. open": "227.3700",
            "2. high": "227.9400",
            "3. low": "226.9900",
            "4. close": "227.0900",
            "5. volume": "343880"
        },
        "2025-10-09 10:00:00": {
            "1. open": "225.9800",
            "2. high": "227.6300",
            "3. low": "225.8500",
            "4. close": "227.3200",
            "5. volume": "431780"
        },
        "2025-10-08 15:00:00": {
            "1. open": "226.3150",
            "2. high": "226.8800",
            "3. low": "226.1500",
            "4. close": "226.6200",
            "5. volume": "1046049"
        },
        "2025-10-08 14:00:00": {
            "1. open": "226.0600",
            "2. high": "226.5500",
            "3. low": "225.8700",
            "4. close": "226.3200",
            "5. volume": "226321"
        },
        "2025-10-08 13:00:00": {
            "1. open": "226.3000",
            "2. high": "226.5600",
            "3. low": "225.8500",
            "4. close": "226.0600",
            "5. volume": "208649"
        },
        "2025-10-08 12:00:00": {
            "1. open": "225.7300",
            "2. high": "226.7600",
            "3. low": "225.6300",
            "4. close": "226.3006",
            "5. volume": "219569"
        },
        "2025-10-08 11:00:00": {
            "1. open": "225.6100",
            "2. high": "226.0400",
            "3. low": "225.2300",
            "4. close": "225.6850",
            "5. volume": "357933"
        },
        "2025-10-08 10:00:00": {
            "1. open": "225.5800",
            "2. high": "226.1600",
            "3. low": "225.0800",
            "4. close": "225.6000",
            "5. volume": "406797"
        },
        "2025-10-07 15:00:00": {
            "1. open": "227.8600",
            "2. high": "228.3100",
            "3. low": "226.8420",
            "4. close": "227.6600",
            "5. volume": "970889"
        },
        "2025-10-07 14:00:00": {
            "1. open": "228.0050",
            "2. high": "228.2500",
            "3. low": "227.5000",
            "4. close": "227.8300",
            "5. volume": "302416"
        },
        "2025-10-07 13:00:00": {
            "1. open": "228.3050",
            "2. high": "228.7500",
            "3. low": "227.8910",
            "4. close": "228.0200",
            "5. volume": "270552"
        },
        "2025-10-07 12:00:00": {
            "1. open": "228.7050",
            "2. high": "228.7050",
            "3. low": "227.8500",
            "4. close": "228.2991",
            "5. volume": "338281"
        },
        "2025-10-07 11:00:00": {
            "1. open": "226.1500",
            "2. high": "228.9450",
            "3. low": "225.9300",
            "4. close": "228.7050",
            "5. volume": "484795"
        },
        "2025-10-07 10:00:00": {
            "1. open": "225.4300",
            "2. high": "227.1100",
            "3. low": "225.3500",
            "4. close": "226.2450",
            "5. volume": "383108"
        },
        "2025-10-06 15:00:00": {
            "1. open": "224.0000",
            "2. high": "225.4900",
            "3. low": "223.4000",
            "4. close": "224.9500",
            "5. volume": "1274170"
        },
        "2025-10-06 14:00:00": {
            "1. open": "222.7400",
            "2. high": "224.2600",
            "3. low": "222.6500",
            "4. close": "224.0300",
            "5. volume": "421179"
        },
        "2025-10-06 13:00:00": {
            "1. open": "222.9100",
            "2. high": "223.1400",
            "3. low": "222.2600",
            "4. close": "222.7300",
            "5. volume": "607895"
        },
        "2025-10-06 12:00:00": {
            "1. open": "223.9400",
            "2. high": "224.1900",
            "3. low": "222.8000",
            "4. close": "222.9050",
            "5. volume": "528823"
        },
        "2025-10-06 11:00:00": {
            "1. open": "224.5250",
            "2. high": "224.9000",
            "3. low": "223.8000",
            "4. close": "224.0400",
            "5. volume": "472538"
        },
        "2025-10-06 10:00:00": {
            "1. open": "225.0900",
            "2. high": "225.6050",
            "3. low": "224.3000",
            "4. close": "224.5175",
            "5. volume": "680929"
        },
        "2025-10-03 15:00:00": {
            "1. open": "228.9700",
            "2. high": "230.3400",
            "3. low": "228.7400",
            "4. close": "230.2600",
            "5. volume": "827274"
        },
        "2025-10-03 14:00:00": {
            "1. open": "229.4300",
            "2. high": "229.9900",
            "3. low": "228.9400",
            "4. close": "228.9700",
            "5. volume": "310167"
        },
        "2025-10-03 13:00:00": {
            "1. open": "228.1750",
            "2. high": "229.4800",
            "3. low": "227.8800",
            "4. close": "229.3800",
            "5. volume": "439810"
        },
        "2025-10-03 12:00:00": {
            "1. open": "228.6900",
            "2. high": "228.9400",
            "3. low": "228.0000",
            "4. close": "228.2800",
            "5. volume": "247813"
        },
        "2025-10-03 11:00:00": {
            "1. open": "228.2800",
            "2. high": "229.5000",
            "3. low": "227.8250",
            "4. close": "228.6600",
            "5. volume": "499731"
        },
        "2025-10-03 10:00:00": {
            "1. open": "228.3850",
            "2. high": "228.9900",
            "3. low": "227.1100",
            "4. close": "228.3250",
            "5. volume": "518532"
        },
        "2025-10-02 15:00:00": {
            "1. open": "230.5000",
            "2. high": "230.5150",
            "3. low": "229.7200",
            "4. close": "230.1300",
            "5. volume": "888749"
        },
        "2025-10-02 14:00:00": {
            "1. open": "230.1700",
            "2. high": "230.8900",
            "3. low": "230.0600",
            "4. close": "230.4900",
            "5. volume": "291779"
        },
        "2025-10-02 13:00:00": {
            "1. open": "230.7400",
            "2. high": "230.8251",
            "3. low": "230.1350",
            "4. close": "230.1350",
            "5. volume": "244131"
        },
        "2025-10-02 12:00:00": {
            "1. open": "230.7225",
            "2. high": "231.0682",
            "3. low": "230.3200",
            "4. close": "230.7925",
            "5. volume": "254072"
        },
        "2025-10-02 11:00:00": {
            "1. open": "231.2700",
            "2. high": "231.4300",
            "3. low": "229.8900",
            "4. close": "230.7150",
            "5. volume": "401420"
        },
        "2025-10-02 10:00:00": {
            "1. open": "230.6650",
            "2. high": "231.5700",
            "3. low": "229.9350",
            "4. close": "231.2750",
            "5. volume": "531600"
        },
        "2025-10-01 15:00:00": {
            "1. open": "233.4150",
            "2. high": "234.1700",
            "3. low": "232.9050",
            "4. close": "233.2400",
            "5. volume": "1037914"
        },
        "2025-10-01 14:00:00": {
            "1. open": "232.0950",
            "2. high": "233.9300",
            "3. low": "231.8100",
            "4. close": "233.4200",
            "5. volume": "478956"
        },
        "2025-10-01 13:00:00": {
            "1. open": "232.6250",
            "2. high": "234.0000",
            "3. low": "231.5550",
            "4. close": "232.0816",
            "5. volume": "713557"
        },
        "2025-10-01 12:00:00": {
            "1. open": "235.7800",
            "2. high": "235.8400",
            "3. low": "232.0300",
            "4. close": "232.6250",
            "5. volume": "649615"
        },
        "2025-10-01 11:00:00": {
            "1. open": "237.4300",
            "2. high": "237.6300",
            "3. low": "235.6400",
            "4. close": "235.7050",
            "5. volume": "414048"
        },
        "2025-10-01 10:00:00": {
            "1. open": "238.9000",
            "2. high": "239.3900",
            "3. low": "236.9400",
            "4. close": "237.4800",
            "5. volume": "589325"
        },
        "2025-10-31 15:00:00": {
            "1. open": "209.5300",
            "2. high": "210.2600",
            "3. low": "209.2750",
            "4. close": "210.1500",
            "5. volume": "955366"
        },
        "2025-10-31 14:00:00": {
            "1. open": "208.9900",
            "2. high": "209.8100",
            "3. low": "208.6350",
            "4. close": "209.5300",
            "5. volume": "505040"
        },
        "2025-10-31 13:00:00": {
            "1. open": "209.8900",
            "2. high": "210.2300",
            "3. low": "208.7101",
            "4. close": "208.9300",
            "5. volume": "537131"
        },
        "2025-10-31 12:00:00": {
            "1. open": "211.5800",
            "2. high": "211.6200",
            "3. low": "209.2700",
            "4. close": "209.9200",
            "5. volume": "518651"
        },
        "2025-10-31 11:00:00": {
            "1. open": "210.7500",
            "2. high": "211.8450",
            "3. low": "210.5300",
            "4. close": "211.5800",
            "5. volume": "371281"
        },
        "2025-10-31 10:00:00": {
            "1. open": "210.4300",
            "2. high": "211.3250",
            "3. low": "209.4300",
            "4. close": "210.7450",
            "5. volume": "479039"
        },
        "2025-11-03 15:00:00": {
            "1. open": "203.3600",
            "2. high": "203.9600",
            "3. low": "202.7300",
            "4. close": "203.2900",
            "5. volume": "1493505"
        },
        "2025-11-03 14:00:00": {
            "1. open": "204.7050",
            "2. high": "204.8000",
            "3. low": "203.2050",
            "4. close": "203.4100",
            "5. volume": "677248"
        },
        "2025-11-03 13:00:00": {
            "1. open": "204.9900",
            "2. high": "206.0900",
            "3. low": "204.4001",
            "4. close": "204.6700",
            "5. volume": "633990"
        },
        "2025-11-03 12:00:00": {
            "1. open": "204.3950",
            "2. high": "205.1250",
            "3. low": "204.1800",
            "4. close": "205.0351",
            "5. volume": "388421"
        },
        "2025-11-03 11:00:00": {
            "1. open": "205.1650",
            "2. high": "205.2800",
            "3. low": "203.7800",
            "4. close": "204.3950",
            "5. volume": "646266"
        },
        "2025-11-03 10:00:00": {
            "1. open": "204.7900",
            "2. high": "206.2000",
            "3. low": "204.0100",
            "4. close": "205.1650",
            "5. volume": "854864"
        },
        "2025-11-05 15:00:00": {
            "1. open": "204.9300",
            "2. high": "205.2000",
            "3. low": "204.5700",
            "4. close": "204.7100",
            "5. volume": "703946"
        },
        "2025-11-05 14:00:00": {
            "1. open": "204.3900",
            "2. high": "204.9800",
            "3. low": "204.3801",
            "4. close": "204.9091",
            "5. volume": "266975"
        },
        "2025-11-05 13:00:00": {
            "1. open": "204.5200",
            "2. high": "204.7500",
            "3. low": "204.1100",
            "4. close": "204.3800",
            "5. volume": "452937"
        },
        "2025-11-05 12:00:00": {
            "1. open": "204.7600",
            "2. high": "205.1800",
            "3. low": "204.4264",
            "4. close": "204.5500",
            "5. volume": "207826"
        },
        "2025-11-05 11:00:00": {
            "1. open": "204.8740",
            "2. high": "204.9400",
            "3. low": "204.2488",
            "4. close": "204.7700",
            "5. volume": "282642"
        },
        "2025-11-05 10:00:00": {
            "1. open": "205.6800",
            "2. high": "206.5200",
            "3. low": "204.1700",
            "4. close": "204.8100",
            "5. volume": "383085"
        },
        "2025-11-04 15:00:00": {
            "1. open": "205.7200",
            "2. high": "206.8500",
            "3. low": "205.5625",
            "4. close": "206.2100",
            "5. volume": "1277200"
        },
        "2025-11-04 14:00:00": {
            "1. open": "205.2300",
            "2. high": "205.9300",
            "3. low": "204.7600",
            "4. close": "205.7450",
            "5. volume": "357624"
        },
        "2025-11-04 13:00:00": {
            "1. open": "205.4200",
            "2. high": "206.1500",
            "3. low": "204.8300",
            "4. close": "205.2200",
            "5. volume": "379410"
        },
        "2025-11-04 12:00:00": {
            "1. open": "205.1400",
            "2. high": "205.7299",
            "3. low": "204.7300",
            "4. close": "205.4300",
            "5. volume": "384002"
        },
        "2025-11-04 11:00:00": {
            "1. open": "205.2500",
            "2. high": "205.8700",
            "3. low": "204.8750",
            "4. close": "205.1400",
            "5. volume": "338656"
        },
        "2025-11-04 10:00:00": {
            "1. open": "205.1500",
            "2. high": "205.8400",
            "3. low": "204.4100",
            "4. close": "205.2300",
            "5. volume": "437526"
        },
        "2025-11-06 15:00:00": {
            "1. open": "201.6300",
            "2. high": "201.6800",
            "3. low": "200.3200",
            "4. close": "201.0100",
            "5. volume": "1236152"
        },
        "2025-11-06 14:00:00": {
            "1. open": "201.8000",
            "2. high": "202.1700",
            "3. low": "201.5400",
            "4. close": "201.6196",
            "5. volume": "445333"
        },
        "2025-11-06 13:00:00": {
            "1. open": "201.1550",
            "2. high": "201.8650",
            "3. low": "200.4500",
            "4. close": "201.8650",
            "5. volume": "421306"
        },
        "2025-11-06 12:00:00": {
            "1. open": "201.4000",
            "2. high": "201.5900",
            "3. low": "200.5800",
            "4. close": "201.1725",
            "5. volume": "576003"
        },
        "2025-11-06 11:00:00": {
            "1. open": "202.2000",
            "2. high": "202.7400",
            "3. low": "201.3500",
            "4. close": "201.3500",
            "5. volume": "536481"
        },
        "2025-11-06 10:00:00": {
            "1. open": "201.6550",
            "2. high": "202.3700",
            "3. low": "199.4100",
            "4. close": "202.2000",
            "5. volume": "1059629"
        }
    }
}